pygamebg.py
PygameBg-0.9.3.dist-info/LICENSE
PygameBg-0.9.3.dist-info/METADATA
PygameBg-0.9.3.dist-info/WHEEL
PygameBg-0.9.3.dist-info/top_level.txt
PygameBg-0.9.3.dist-info/zip-safe
PygameBg-0.9.3.dist-info/RECORD
