Metadata-Version: 2.1
Name: PygameBg
Version: 0.9.3
Summary: Pygame Toolbox for Beginners by Petlja
Home-page: https://github.com/Petlja/PygameBg
Author: Fondacija Petlja
Author-email: team@petlja.org
License: UNKNOWN
Platform: UNKNOWN
Classifier: Programming Language :: Python :: 3
Classifier: License :: OSI Approved :: MIT License
Classifier: Operating System :: OS Independent
Requires-Python: >=3
Requires-Dist: pygame (>=1.9.6)
